endway_api/__init__.py
endway_api/endway_api.py
endway_api-1.0.dist-info/LICENSE
endway_api-1.0.dist-info/METADATA
endway_api-1.0.dist-info/WHEEL
endway_api-1.0.dist-info/top_level.txt
endway_api-1.0.dist-info/RECORD
